setup.py
tompoes.py
scripts/tom
tompoes.egg-info/PKG-INFO
tompoes.egg-info/SOURCES.txt
tompoes.egg-info/dependency_links.txt
tompoes.egg-info/entry_points.txt
tompoes.egg-info/not-zip-safe
tompoes.egg-info/requires.txt
tompoes.egg-info/top_level.txt