Metadata-Version: 1.0
Name: tompoes
Version: 0.0.5
Summary: It is impossible to properly install this package as a develop egg or a mr.developer source, in buildout 2.0
Home-page: UNKNOWN
Author: Lars van de Kerkhof
Author-email: lars@permanentmarkers.nl
License: Public Domain
Platform: UNKNOWN
